pywebvue/LICENSE
pywebvue/__init__.py
pywebvue/core.py
pywebvue/protocol.py
pywebvue/builders/__init__.py
pywebvue/modules/__init__.py
pywebvue/modules/AGGrid/__init__.py
pywebvue/modules/AGGrid/serve/.gitignore
pywebvue/modules/AGGrid/serve/vue-ag-grid.css
pywebvue/modules/AGGrid/serve/vue-ag-grid.umd.min.js
pywebvue/modules/CDNVegaLite/__init__.py
pywebvue/modules/Deck/__init__.py
pywebvue/modules/Deck/serve/.gitignore
pywebvue/modules/Deck/serve/vue-deck.umd.min.js
pywebvue/modules/Markdown/__init__.py
pywebvue/modules/Markdown/serve/markdown-it-vue.css
pywebvue/modules/Markdown/serve/markdown-it-vue.umd.min.js
pywebvue/modules/Markdown/serve/fonts/element-icons.535877f5.woff
pywebvue/modules/Markdown/serve/fonts/element-icons.732389de.ttf
pywebvue/modules/Markdown/serve/fonts/fontawesome-webfont.674f50d2.eot
pywebvue/modules/Markdown/serve/fonts/fontawesome-webfont.af7ae505.woff2
pywebvue/modules/Markdown/serve/fonts/fontawesome-webfont.b06871f2.ttf
pywebvue/modules/Markdown/serve/fonts/fontawesome-webfont.fee66e71.woff
pywebvue/modules/Markdown/serve/img/fontawesome-webfont.912ec66d.svg
pywebvue/modules/Matplotlib/__init__.py
pywebvue/modules/Matplotlib/serve/d3.placeholder.js
pywebvue/modules/Matplotlib/serve/d3.v5.min.js
pywebvue/modules/Matplotlib/serve/mpld3.v0.5.7.min.js
pywebvue/modules/Matplotlib/serve/vue-mpld3.umd.min.js
pywebvue/modules/ParaView/__init__.py
pywebvue/modules/ParaView/core.py
pywebvue/modules/Plotly/__init__.py
pywebvue/modules/Plotly/serve/demo.html
pywebvue/modules/Plotly/serve/vue-plotly.umd.min.js
pywebvue/modules/Router/__init__.py
pywebvue/modules/SizeObserver/__init__.py
pywebvue/modules/SizeObserver/serve/vue-size.umd.min.js
pywebvue/modules/VTK/__init__.py
pywebvue/modules/VTK/addon_serializer.py
pywebvue/modules/VTK/core.py
pywebvue/modules/VegaEmbed/__init__.py
pywebvue/modules/VegaEmbed/serve/.gitignore
pywebvue/modules/VegaEmbed/serve/vue-vega-embed.umd.min.js
pywebvue/modules/VegaLite/__init__.py
pywebvue-2.11.5.dist-info/METADATA
pywebvue-2.11.5.dist-info/WHEEL
pywebvue-2.11.5.dist-info/top_level.txt
pywebvue-2.11.5.dist-info/RECORD
