Metadata-Version: 2.1
Name: pywebvue
Version: 2.11.5
Summary: Python server creating interactive vue app over WebSocket
Home-page: https://github.com/kitware/py-web-vue
Author: Kitware, Inc.
Author-email: kitware@kitware.com
License: BSD-3-Clause
Keywords: Python,Vue.js,websocket,VTK,ParaView,Web3D
Platform: UNKNOWN
Classifier: Development Status :: 5 - Production/Stable
Classifier: Environment :: Web Environment
Classifier: License :: OSI Approved :: BSD License
Classifier: Natural Language :: English
Classifier: Operating System :: OS Independent
Classifier: Programming Language :: Python :: 3 :: Only
Classifier: Programming Language :: JavaScript
Classifier: Topic :: Software Development :: Libraries :: Application Frameworks
Classifier: Topic :: Software Development :: Libraries :: Python Modules
Requires-Dist: wslink (>=1.2.0)
